purecpp_huggingface_embedding/__init__.py
purecpp_huggingface_embedding/embedding.py
purecpp_huggingface_embedding-0.1.0.dist-info/licenses/LICENSE
purecpp_huggingface_embedding-0.1.0.dist-info/METADATA
purecpp_huggingface_embedding-0.1.0.dist-info/WHEEL
purecpp_huggingface_embedding-0.1.0.dist-info/top_level.txt
purecpp_huggingface_embedding-0.1.0.dist-info/RECORD
