Metadata-Version: 2.4
Name: purecpp-huggingface-embedding
Version: 0.1.0
Summary: A Python package for generating text embeddings using Hugging Face models.
Author-email: PureAI <contato@pureai.com.br>
License-Expression: MIT
Requires-Python: >=3.9
License-File: LICENSE
Requires-Dist: transformers
Requires-Dist: sentence-transformers
Requires-Dist: torch
Provides-Extra: dev
Requires-Dist: pytest; extra == "dev"
Requires-Dist: pytest-asyncio; extra == "dev"
Requires-Dist: respx; extra == "dev"
Requires-Dist: ruff; extra == "dev"
Requires-Dist: mypy; extra == "dev"
Requires-Dist: types-requests; extra == "dev"
Dynamic: license-file
